python_rest_client_codegen/__init__.py
python_rest_client_codegen/codegen.py
python_rest_client_codegen/openapi-generator-cli.jar
python_rest_client_codegen/python-rest-client-codegen-tests.jar
python_rest_client_codegen/python-rest-client-codegen.jar
python_rest_client_codegen-1.8.0.dist-info/METADATA
python_rest_client_codegen-1.8.0.dist-info/WHEEL
python_rest_client_codegen-1.8.0.dist-info/top_level.txt
python_rest_client_codegen-1.8.0.dist-info/RECORD
