Metadata-Version: 2.1
Name: python-rest-client-codegen
Version: 1.8.0
Summary: Python rest client codegen for Le Comptoir Des Pharmacies
Home-page: https://bitbucket.org/lecomptoirdespharmacies/lcdp-openapi-codegen
Author: Le Comptoir Des Pharmacies
Author-email: g.thrasibule@lecomptoirdespharmacies.fr
License: Apache-2.0
Keywords: openapi,python-rest-client-codegen,openapi3
Platform: UNKNOWN
Requires-Dist: pydantic (==2.9.2)
